MANIFEST.in
README.rst
setup.py
gyun/__init__.py
gyun/app/__init__.py
gyun/app/connection.py
gyun/app/constants.py
gyun/conn/__init__.py
gyun/conn/auth.py
gyun/conn/connection.py
gyun/gomestor/__init__.py
gyun/gomestor/acl.py
gyun/gomestor/bucket.py
gyun/gomestor/connection.py
gyun/gomestor/exception.py
gyun/gomestor/key.py
gyun/gomestor/multipart.py
gyun/gomestor/util.py
gyun/iaas/__init__.py
gyun/iaas/connection.py
gyun/iaas/consolidator.py
gyun/iaas/constants.py
gyun/iaas/errors.py
gyun/iaas/lb_backend.py
gyun/iaas/lb_listener.py
gyun/iaas/monitor.py
gyun/iaas/router_static.py
gyun/iaas/sg_rule.py
gyun/iaas/actions/__init__.py
gyun/iaas/actions/alarm_policy.py
gyun/iaas/actions/nic.py
gyun/iaas/actions/s2.py
gyun/misc/__init__.py
gyun/misc/json_tool.py
gyun/misc/utils.py
gyun_sdk.egg-info/PKG-INFO
gyun_sdk.egg-info/SOURCES.txt
gyun_sdk.egg-info/dependency_links.txt
gyun_sdk.egg-info/namespace_packages.txt
gyun_sdk.egg-info/requires.txt
gyun_sdk.egg-info/top_level.txt