Metadata-Version: 1.0
Name: gyun-sdk
Version: 1.1.2
Summary: Software Development Kit for GYUN.
Home-page: https://docs.qc.gyun.com/sdk/
Author: GYUN Team
Author-email: service@gomeholdings.com
License: UNKNOWN
Keywords: gyun iaas gomestor sdk
Platform: UNKNOWN
